eagerx_reality/__init__.py
eagerx_reality/engine.py
eagerx_reality/enginenodes.py
eagerx_reality-0.1.12.dist-info/LICENSE
eagerx_reality-0.1.12.dist-info/WHEEL
eagerx_reality-0.1.12.dist-info/METADATA
eagerx_reality-0.1.12.dist-info/RECORD
