Metadata-Version: 2.1
Name: eagerx-reality
Version: 0.1.12
Summary: Simple engine that can be used in reality together with several useful nodes.
Home-page: https://github.com/eager-dev/eagerx_reality
License: Apache2.0
Author: Jelle Luijkx
Author-email: j.d.luijkx@tudelft.nl
Requires-Python: >=3.6.2,<4.0.0
Classifier: License :: Other/Proprietary License
Classifier: Programming Language :: Python :: 3
Classifier: Programming Language :: Python :: 3.7
Classifier: Programming Language :: Python :: 3.8
Classifier: Programming Language :: Python :: 3.9
Classifier: Programming Language :: Python :: 3.10
Requires-Dist: eagerx (>=0.1.32,<0.2.0)
Project-URL: Documentation, https://eagerx.readthedocs.io/en/master/
Project-URL: Repository, https://github.com/eager-dev/eagerx_reality
